{
  "comparison_date": "2025-09-30",
  "country": "KU",
  "total_current_promotions": 5,
  "total_previous_promotions": 0,
  "new_promotions_count": 5,
  "removed_promotions_count": 0,
  "competitors_analyzed": [
    "888 Casino",
    "CoinCasino",
    "CasinoMega"
  ],
  "new_promotions": [
    {
      "id": 111,
      "competitor": "888 Casino",
      "country": "KU",
      "title": "888 Casino Canada | Fast Login and Secure Registration\nSign InSign UpConnectNo Deposit Bonus – C$88 ",
      "description": "888 Casino Canada | Fast Login and Secure Registration\nSign InSign UpConnectNo Deposit Bonus – C$88 FreeGET BONUSLog in 888Casino Official Ready for a thrill? 888 Casino is your gateway to top-tier online gaming in Canada",
      "bonus_amount": "$88",
      "bonus_type": "Deposit Bonus",
      "conditions": "",
      "valid_until": "",
      "url": "https://888-casino.org",
      "scraped_at": "2025-09-30T10:16:10.466057",
      "hash_id": "695825573547626007",
      "is_active": 1,
      "created_at": "2025-09-30 08:17:31"
    },
    {
      "id": 115,
      "competitor": "CasinoMega",
      "country": "KU",
      "title": "\n\n\n\n\n\n\n\n\n\n\n\n\n\n\n\n\n\n\n\n\n\n\n\n\n\n\n\n\n\n\n\n\n\n\n\n\n\n\n\n\n\n\nOnline Casino Bonuses - Sport Betting Bonuses | CasinoMeg",
      "description": "\n\n\n\n\n\n\n\n\n\n\n\n\n\n\n\n\n\n\n\n\n\n\n\n\n\n\n\n\n\n\n\n\n\n\n\n\n\n\n\n\n\n\nOnline Casino Bonuses - Sport Betting Bonuses | CasinoMega\n\n\n\n\n\n\n \n\n\n\n\n\n\n\n\n\n\n\n\n\n\n\n\n\n\n\n\n\n\n\n\n\n\n\n\n\n\n\n\n\n\n\n\n\n\n\n\n\n\n\n\n\n\n\n\n\n\n\n\n\n\n\n\n\n\n\n\n\n\n\n\n\nLogin\n\n\nRegister\n\n\n\n\n\n\r\n                                VIP\r\n                            \n\n\n\n\nen\npl\nde\nar\nch\n\n\n\n\n\n\n\n\n\n\n\n\n\n\n\n\n\n\n\n\n\n\n\n\r\n                        Casino\r\n                    \n\n\n\n\r\n                        Live Casino\r\n                    \n\n\n\n\r\n                        Sports\r\n                    \n\n\n\n\r\n            ",
      "bonus_amount": "€500",
      "bonus_type": "Welcome Bonus",
      "conditions": "",
      "valid_until": "",
      "url": "https://casinomega.com/welcome-bonus",
      "scraped_at": "2025-09-30T10:16:41.462369",
      "hash_id": "-290982260724601727",
      "is_active": 1,
      "created_at": "2025-09-30 08:17:31"
    },
    {
      "id": 113,
      "competitor": "CasinoMega",
      "country": "KU",
      "title": "\n\n\n\n\n\n\n\n\n\n\n\n\n\n\n\n\n\n\n\n\n\n\n\n\n\n\n\n\n\n\n\n\n\n\n\n\n\n\n\n\n\n\nThe Best Online Casino Games - Online Casino | CasinoMega",
      "description": "\n\n\n\n\n\n\n\n\n\n\n\n\n\n\n\n\n\n\n\n\n\n\n\n\n\n\n\n\n\n\n\n\n\n\n\n\n\n\n\n\n\n\nThe Best Online Casino Games - Online Casino | CasinoMega\n\n\n\n\n\n\n \n\n\n\n\n\n\n\n\n\n\n\n\n\n\n\n\n\n\n\n\n\n\n\n\n\n\n\n\n\n\n\n\n\n\n\n\n\n\n\n\n\n\n\n\n\n\n\n\n\n\n\n\n\n\n\n\n\n\n\n\n\n\n\n\n\n\nLogin\n\n\nRegister\n\n\n\n\n\n\r\n                                VIP\r\n                            \n\n\n\n\nen\npl\nde\nar\nch\n\n\n\n\n\n\n\n\n\n\n\n\n\n\n\n\n\n\n\n\n\n\n\n\r\n                        Casino\r\n                    \n\n\n\n\r\n                        Live Casino\r\n                    \n\n\n\n\r\n                        Sports\r\n                    \n\n\n\n\r\n            ",
      "bonus_amount": "",
      "bonus_type": "Other",
      "conditions": "",
      "valid_until": "",
      "url": "https://casinomega.com/tournaments",
      "scraped_at": "2025-09-30T10:16:42.676288",
      "hash_id": "-4174357552481642681",
      "is_active": 1,
      "created_at": "2025-09-30 08:17:31"
    },
    {
      "id": 114,
      "competitor": "CasinoMega",
      "country": "KU",
      "title": "\nBonus Çevrim Şartları\nBahis sitelerinin asla vazgeçilmez kampanyaları vardır",
      "description": "\nBonus Çevrim Şartları\nBahis sitelerinin asla vazgeçilmez kampanyaları vardır",
      "bonus_amount": "",
      "bonus_type": "Other",
      "conditions": "",
      "valid_until": "",
      "url": "https://www.casinomega.net",
      "scraped_at": "2025-09-30T10:16:34.985195",
      "hash_id": "9187084169199677598",
      "is_active": 1,
      "created_at": "2025-09-30 08:17:31"
    },
    {
      "id": 112,
      "competitor": "CoinCasino",
      "country": "KU",
      "title": "    Coin Casino — Login, Get up to €1,000 + 100 FS                                       Games Sport",
      "description": "    Coin Casino — Login, Get up to €1,000 + 100 FS                                       Games Sport Cybersport Promo Tournaments Lotteries   Login Sign Up                       Login Sign Up   Games Sport Cybersport Promo Tournaments Lotteries       Coincasino Coincasino stands as one of the most innovative and player-focused online casinos in the UK market today",
      "bonus_amount": "€1,000",
      "bonus_type": "Tournament",
      "conditions": "",
      "valid_until": "",
      "url": "https://coincasino.casino",
      "scraped_at": "2025-09-30T10:16:13.158816",
      "hash_id": "613897891341547160",
      "is_active": 1,
      "created_at": "2025-09-30 08:17:31"
    }
  ]
}